{
	"info": {
		"_postman_id": "4058d55c-d925-48be-b38f-99265592cd23",
		"name": "Publishing House",
		"schema": "https://schema.getpostman.com/json/collection/v2.1.0/collection.json"
	},
	"item": [
		{
			"name": "Author",
			"item": [
				{
					"name": "addAuthor",
					"request": {
						"method": "POST",
						"header": [],
						"body": {
							"mode": "raw",
							"raw": "{\n\t\"name\": \"shoes\",\n\t\"description\": \"black\",\n\t\"shopName\": \"bestseller\"\n}",
							"options": {
								"raw": {
									"language": "json"
								}
							}
						},
						"url": {
							"raw": "localhost:8080/api/author",
							"host": [
								"localhost"
							],
							"port": "8080",
							"path": [
								"api",
								"author"
							]
						}
					},
					"response": []
				},
				{
					"name": "getAllAuthors",
					"protocolProfileBehavior": {
						"disableBodyPruning": true
					},
					"request": {
						"method": "GET",
						"header": [],
						"body": {
							"mode": "raw",
							"raw": "{\n\t\"firstName\": \"irina\",\n\t\"lastName\": \"binder\",\n\t\"bookVersion\": \"1\",\n\t\"category\": \"bestseller\"\n}",
							"options": {
								"raw": {
									"language": "json"
								}
							}
						},
						"url": {
							"raw": "localhost:8080/api/author",
							"host": [
								"localhost"
							],
							"port": "8080",
							"path": [
								"api",
								"author"
							]
						}
					},
					"response": []
				},
				{
					"name": "getAuthorById",
					"protocolProfileBehavior": {
						"disableBodyPruning": true
					},
					"request": {
						"method": "GET",
						"header": [],
						"body": {
							"mode": "raw",
							"raw": "",
							"options": {
								"raw": {
									"language": "json"
								}
							}
						},
						"url": {
							"raw": "localhost:8080/api/author",
							"host": [
								"localhost"
							],
							"port": "8080",
							"path": [
								"api",
								"author"
							]
						}
					},
					"response": []
				},
				{
					"name": "addAuthorToPublishingHouse",
					"request": {
						"method": "PUT",
						"header": [],
						"body": {
							"mode": "raw",
							"raw": "\"3\"",
							"options": {
								"raw": {
									"language": "json"
								}
							}
						},
						"url": {
							"raw": "localhost:8080/api/author/3",
							"host": [
								"localhost"
							],
							"port": "8080",
							"path": [
								"api",
								"author",
								"3"
							]
						}
					},
					"response": []
				},
				{
					"name": "getAllAuthorsByPublishingH",
					"protocolProfileBehavior": {
						"disableBodyPruning": true
					},
					"request": {
						"method": "GET",
						"header": [],
						"body": {
							"mode": "raw",
							"raw": "{\n\t\"firstName\": \"irina\",\n\t\"lastName\": \"binder\",\n\t\"bookVersion\": \"1\",\n\t\"category\": \"bestseller\"\n}",
							"options": {
								"raw": {
									"language": "json"
								}
							}
						},
						"url": {
							"raw": "localhost:8080/api/author",
							"host": [
								"localhost"
							],
							"port": "8080",
							"path": [
								"api",
								"author"
							]
						}
					},
					"response": []
				},
				{
					"name": "deleteAuthorById",
					"request": {
						"method": "DELETE",
						"header": [],
						"body": {
							"mode": "raw",
							"raw": "{\n\t\"firstName\": \"irina\",\n\t\"lastName\": \"binder\",\n\t\"bookVersion\": \"1\",\n\t\"category\": \"bestseller\"\n}",
							"options": {
								"raw": {
									"language": "json"
								}
							}
						},
						"url": {
							"raw": "localhost:8080/api/author",
							"host": [
								"localhost"
							],
							"port": "8080",
							"path": [
								"api",
								"author"
							]
						}
					},
					"response": []
				},
				{
					"name": "updateAuthorById",
					"request": {
						"method": "PUT",
						"header": [],
						"body": {
							"mode": "raw",
							"raw": "{\n\t\"firstName\": \"irina\",\n\t\"lastName\": \"binder\",\n\t\"bookVersion\": \"1\",\n\t\"category\": \"bestseller\"\n}",
							"options": {
								"raw": {
									"language": "json"
								}
							}
						},
						"url": {
							"raw": "localhost:8080/api/author",
							"host": [
								"localhost"
							],
							"port": "8080",
							"path": [
								"api",
								"author"
							]
						}
					},
					"response": []
				}
			],
			"protocolProfileBehavior": {}
		},
		{
			"name": "PublishingH",
			"item": [
				{
					"name": "addPublishingHouse",
					"request": {
						"method": "POST",
						"header": [],
						"body": {
							"mode": "raw",
							"raw": "{\n\t\"name\": \"fly\",\n\t\"location\": \"pitesti\"\n}",
							"options": {
								"raw": {
									"language": "json"
								}
							}
						},
						"url": {
							"raw": "localhost:8080/api/publishingH",
							"host": [
								"localhost"
							],
							"port": "8080",
							"path": [
								"api",
								"publishingH"
							]
						}
					},
					"response": []
				},
				{
					"name": "getAllPublishingHouses",
					"protocolProfileBehavior": {
						"disableBodyPruning": true
					},
					"request": {
						"method": "GET",
						"header": [],
						"body": {
							"mode": "raw",
							"raw": "{\n\t\"name\": \"fly\",\n\t\"location\": \"pitesti\"\n}",
							"options": {
								"raw": {
									"language": "json"
								}
							}
						},
						"url": {
							"raw": "localhost:8080/api/publishingH",
							"host": [
								"localhost"
							],
							"port": "8080",
							"path": [
								"api",
								"publishingH"
							]
						}
					},
					"response": []
				},
				{
					"name": "getPublishingHouseById",
					"protocolProfileBehavior": {
						"disableBodyPruning": true
					},
					"request": {
						"method": "GET",
						"header": [],
						"body": {
							"mode": "raw",
							"raw": "{\n\t\"name\": \"fly\",\n\t\"location\": \"pitesti\"\n}",
							"options": {
								"raw": {
									"language": "json"
								}
							}
						},
						"url": {
							"raw": "localhost:8080/api/publishingH",
							"host": [
								"localhost"
							],
							"port": "8080",
							"path": [
								"api",
								"publishingH"
							]
						}
					},
					"response": []
				},
				{
					"name": "deletePublishingHouseById",
					"request": {
						"method": "DELETE",
						"header": [],
						"body": {
							"mode": "raw",
							"raw": "{\n\t\"name\": \"fly\",\n\t\"location\": \"pitesti\"\n}",
							"options": {
								"raw": {
									"language": "json"
								}
							}
						},
						"url": {
							"raw": "localhost:8080/api/publishingH/7",
							"host": [
								"localhost"
							],
							"port": "8080",
							"path": [
								"api",
								"publishingH",
								"7"
							]
						}
					},
					"response": []
				},
				{
					"name": "updatePublishingHouseById",
					"request": {
						"method": "PUT",
						"header": [],
						"body": {
							"mode": "raw",
							"raw": "{\n\t\"name\": \"fly\",\n\t\"location\": \"pitesti\"\n}",
							"options": {
								"raw": {
									"language": "json"
								}
							}
						},
						"url": {
							"raw": "localhost:8080/api/publishingH/7",
							"host": [
								"localhost"
							],
							"port": "8080",
							"path": [
								"api",
								"publishingH",
								"7"
							]
						}
					},
					"response": []
				}
			],
			"protocolProfileBehavior": {}
		}
	],
	"protocolProfileBehavior": {}
}